xhb2beancount/__init__.py
xhb2beancount/__version__.py
xhb2beancount/config.py
xhb2beancount/main.py
xhb2beancount/xhb2beancount.py
xhb2beancount-0.1.3.dist-info/LICENSE
xhb2beancount-0.1.3.dist-info/METADATA
xhb2beancount-0.1.3.dist-info/WHEEL
xhb2beancount-0.1.3.dist-info/entry_points.txt
xhb2beancount-0.1.3.dist-info/top_level.txt
xhb2beancount-0.1.3.dist-info/RECORD
