Metadata-Version: 2.1
Name: xhb2beancount
Version: 0.1.3
Summary: Convert Homebank files to Beancount format.
Home-page: https://github.com/kevinzg/xhb2beancount
Author: Kevin Zúñiga
Author-email: kevin.zun@gmail.com
License: MIT
Platform: UNKNOWN
Classifier: License :: OSI Approved :: MIT License
Classifier: Programming Language :: Python
Classifier: Programming Language :: Python :: 3
Classifier: Programming Language :: Python :: 3.6
Classifier: Programming Language :: Python :: Implementation :: CPython
Classifier: Programming Language :: Python :: Implementation :: PyPy
Requires-Python: >=3.6.0
Requires-Dist: beancount
Requires-Dist: untangle
Requires-Dist: text-unidecode
